EasyOutput/EasyOutput.py
EasyOutput/__init__.py
easyoutput-0.1.1.dist-info/METADATA
easyoutput-0.1.1.dist-info/WHEEL
easyoutput-0.1.1.dist-info/licenses/LICENSE.txt
easyoutput-0.1.1.dist-info/RECORD
