Metadata-Version: 2.3
Name: EasyOutput
Version: 0.1.1
Summary: Colored messages in the palm of your hand
Project-URL: Homepage, https://github.com/RasinBrand/EasyOutput/
Project-URL: Issues, https://github.com/RasinBrand/EasyOutput/issues/new/choose
Project-URL: Feature Request, https://github.com/RasinBrand/EasyOutput/issues/new/choose
Author-email: Brandon McKinney <brandonaustinmck01@icloud.com>
Maintainer-email: Brandon McKinney <brandonaustinmck01@icloud.com>
License: MIT License
License-File: LICENSE.txt
Keywords: Colored Messages,Easy,Error Message,Success Message,Warning Message
Classifier: Development Status :: 5 - Production/Stable
Classifier: Intended Audience :: Developers
Classifier: License :: Freeware
Classifier: Operating System :: MacOS :: MacOS X
Classifier: Operating System :: Microsoft :: Windows
Classifier: Operating System :: Unix
Classifier: Programming Language :: Python :: 3
Requires-Python: >=3.12
Requires-Dist: colorama
